Workbook
Name Assets: Asset_table[Amount]
Name Date_range: Resources!$D$2:$D$31
Name date_txn: Txn_table[Date]
Name dateIndex: Resources!$E$2:$E$8
Name Day_num: Resources!$E$2:$E$31
Name net_expense: Summary!$B$12
Name net_income: Summary!$B$9
Name net_profit: Summary!$B$19
Name Orglist: Rate_Table[Organization]
Name Transactions_Table: Txn_table[]
Name Txn_Cat_list: Categories_Table[Category]

Sheet Example Data
D1: Budget Tracking Dashboard
A3: Income
A4: Salary | B4: 100000 | C4: =_xlfn.FORMULATEXT(B4) -> #N/A
A5: tax (20%) | B5: =-15%*B4 -> -15000 | C5: =_xlfn.FORMULATEXT(B5) -> =-15%*B4
A6: Super | B6: =-11%*B4 -> -11000 | C6: =_xlfn.FORMULATEXT(B6) -> =-11%*B4
A7: Insurance | B7: =-8%*B4 -> -8000 | C7: =_xlfn.FORMULATEXT(B7) -> =-8%*B4
A8: Bonus | B8: =5%*B4 -> 5000 | C8: =_xlfn.FORMULATEXT(B8) -> =5%*B4
A9: Net Income | B9: =SUM(B4:B8) -> 71000 | C9: =_xlfn.FORMULATEXT(B9) -> =SUM(B4:B8)
A11: Expense
A12: Net Expense | B12: =SUM(B13:B17) -> 43400
A13: Food | B13: 24000
A14: Rent | B14: 14400
A15: Travel | B15: 3000
A16: Car Petrol | B16: 1000
A17: Mobile Bills | B17: 1000
A19: Net Profit | B19: =B9-B17 -> 70000
A20: % Saving | B20: =(1-B12/B19) -> 0.38
A21: %Expenses | B21: =1-B20 -> 0.62

Sheet Example DashBoard
D2: Budget Tracking Dashboard

Sheet Monthly data
A1: Date | B1: Day | C1: start_time | D1: end_time | E1: Total_time_worked | F1: organization | G1: Money_Earned | H1: Comments | L1: Salary Rate
A2: 45658 | B2: =TEXT(Monthly_Table[[#This Row],[Date]],"ddd") -> Wed | C2: 0.375 | D2: 0.72916667 | E2: =IF( AND(ISBLANK(Monthly_Table[[#This Row],[start_time]]), ISBLANK(Monthly_Table[[#This Row],[end_time]])), "Enter time", IF( AND(ISNUMBER(Monthly_Table[[#This Row],[start_time]]), ISNUMBER(Monthly_Table[[#This Row],[end_time]])), IF( Monthly_Table[[#This Row],[end_time]] >= Monthly_Table[[#This Row],[start_time]], (Monthly_Table[[#This Row],[end_time]] - Monthly_Table[[#This Row],[start_time]]) * 24, "Error: End time before start" ), "Error: Invalid time format" ) ) -> 8.5 | F2: AMPOL | G2: =IF( OR(ISBLANK(Monthly_Table[[#This Row],[Total_time_worked]]), ISBLANK(Monthly_Table[[#This Row],[organization ]])), "Enter time and organization", IF( AND( ISNUMBER(Monthly_Table[[#This Row],[Total_time_worked]]), ISNUMBER(VLOOKUP(Monthly_Table[[#This Row],[organization ]], Rate_Table[], 3, FALSE)) ), ROUND(Monthly_Table[[#This Row],[Total_time_worked]] * VLOOKUP(Monthly_Table[[#This Row],[organization ]], Rate_Table[], 3, FALSE), 2), "Error: Invalid input or missing rate" ) ) -> 263.5 | H2: Example: to be deleted once true data is entered | L2: Organization | M2: Role | N2: Rate | O2: Total_Earned
A3: 45658 | B3: =TEXT(Monthly_Table[[#This Row],[Date]],"ddd") -> Wed | C3: 0.75 | D3: 0.95833333 | E3: =IF( AND(ISBLANK(Monthly_Table[[#This Row],[start_time]]), ISBLANK(Monthly_Table[[#This Row],[end_time]])), "Enter time", IF( AND(ISNUMBER(Monthly_Table[[#This Row],[start_time]]), ISNUMBER(Monthly_Table[[#This Row],[end_time]])), IF( Monthly_Table[[#This Row],[end_time]] >= Monthly_Table[[#This Row],[start_time]], (Monthly_Table[[#This Row],[end_time]] - Monthly_Table[[#This Row],[start_time]]) * 24, "Error: End time before start" ), "Error: Invalid time format" ) ) -> 5 | F3: COLES | G3: =IF( OR(ISBLANK(Monthly_Table[[#This Row],[Total_time_worked]]), ISBLANK(Monthly_Table[[#This Row],[organization ]])), "Enter time and organization", IF( AND( ISNUMBER(Monthly_Table[[#This Row],[Total_time_worked]]), ISNUMBER(VLOOKUP(Monthly_Table[[#This Row],[organization ]], Rate_Table[], 3, FALSE)) ), ROUND(Monthly_Table[[#This Row],[Total_time_worked]] * VLOOKUP(Monthly_Table[[#This Row],[organization ]], Rate_Table[], 3, FALSE), 2), "Error: Invalid input or missing rate" ) ) -> 125 | L3: COLES | M3: Teammember | N3: 25 | O3: =IFERROR(SUMIFS(Monthly_Table[Money_Earned], Monthly_Table[[organization ]], Rate_Table[[#This Row],[Organization]]), 0) -> 625 | Q3: {=_xlfn.UNIQUE(IFERROR(LEFT(Rate_Table[Organization],FIND("_",Rate_Table[Organization])-1),Rate_Table[Organization]))} -> COLES | R3: {=IFERROR(SUMIFS(Rate_Table[Total_Earned], Rate_Table[Organization],_xlfn.ANCHORARRAY( Q3)), 0)} -> 625
A4: 45659 | B4: =TEXT(Monthly_Table[[#This Row],[Date]],"ddd") -> Thu | C4: 0.375 | D4: 0.72916667 | E4: =IF( AND(ISBLANK(Monthly_Table[[#This Row],[start_time]]), ISBLANK(Monthly_Table[[#This Row],[end_time]])), "Enter time", IF( AND(ISNUMBER(Monthly_Table[[#This Row],[start_time]]), ISNUMBER(Monthly_Table[[#This Row],[end_time]])), IF( Monthly_Table[[#This Row],[end_time]] >= Monthly_Table[[#This Row],[start_time]], (Monthly_Table[[#This Row],[end_time]] - Monthly_Table[[#This Row],[start_time]]) * 24, "Error: End time before start" ), "Error: Invalid time format" ) ) -> 8.5 | F4: AMPOL | G4: =IF( OR(ISBLANK(Monthly_Table[[#This Row],[Total_time_worked]]), ISBLANK(Monthly_Table[[#This Row],[organization ]])), "Enter time and organization", IF( AND( ISNUMBER(Monthly_Table[[#This Row],[Total_time_worked]]), ISNUMBER(VLOOKUP(Monthly_Table[[#This Row],[organization ]], Rate_Table[], 3, FALSE)) ), ROUND(Monthly_Table[[#This Row],[Total_time_worked]] * VLOOKUP(Monthly_Table[[#This Row],[organization ]], Rate_Table[], 3, FALSE), 2), "Error: Invalid input or missing rate" ) ) -> 263.5 | L4: AMPOL | M4: Teammember | N4: 31 | O4: =IFERROR(SUMIFS(Monthly_Table[Money_Earned], Monthly_Table[[organization ]], Rate_Table[[#This Row],[Organization]]), 0) -> 1317.5 | Q4: AMPOL | R4: 1317.5
A5: 45659 | B5: =TEXT(Monthly_Table[[#This Row],[Date]],"ddd") -> Thu | C5: 0.75 | D5: 0.95833333 | E5: =IF( AND(ISBLANK(Monthly_Table[[#This Row],[start_time]]), ISBLANK(Monthly_Table[[#This Row],[end_time]])), "Enter time", IF( AND(ISNUMBER(Monthly_Table[[#This Row],[start_time]]), ISNUMBER(Monthly_Table[[#This Row],[end_time]])), IF( Monthly_Table[[#This Row],[end_time]] >= Monthly_Table[[#This Row],[start_time]], (Monthly_Table[[#This Row],[end_time]] - Monthly_Table[[#This Row],[start_time]]) * 24, "Error: End time before start" ), "Error: Invalid time format" ) ) -> 5 | F5: COLES | G5: =IF( OR(ISBLANK(Monthly_Table[[#This Row],[Total_time_worked]]), ISBLANK(Monthly_Table[[#This Row],[organization ]])), "Enter time and organization", IF( AND( ISNUMBER(Monthly_Table[[#This Row],[Total_time_worked]]), ISNUMBER(VLOOKUP(Monthly_Table[[#This Row],[organization ]], Rate_Table[], 3, FALSE)) ), ROUND(Monthly_Table[[#This Row],[Total_time_worked]] * VLOOKUP(Monthly_Table[[#This Row],[organization ]], Rate_Table[], 3, FALSE), 2), "Error: Invalid input or missing rate" ) ) -> 125 | L5: COLES_SPL | M5: Teammember | N5: 28 | O5: =IFERROR(SUMIFS(Monthly_Table[Money_Earned], Monthly_Table[[organization ]], Rate_Table[[#This Row],[Organization]]), 0) -> 280
A6: 45660 | B6: =TEXT(Monthly_Table[[#This Row],[Date]],"ddd") -> Fri | C6: 0.375 | D6: 0.72916667 | E6: =IF( AND(ISBLANK(Monthly_Table[[#This Row],[start_time]]), ISBLANK(Monthly_Table[[#This Row],[end_time]])), "Enter time", IF( AND(ISNUMBER(Monthly_Table[[#This Row],[start_time]]), ISNUMBER(Monthly_Table[[#This Row],[end_time]])), IF( Monthly_Table[[#This Row],[end_time]] >= Monthly_Table[[#This Row],[start_time]], (Monthly_Table[[#This Row],[end_time]] - Monthly_Table[[#This Row],[start_time]]) * 24, "Error: End time before start" ), "Error: Invalid time format" ) ) -> 8.5 | F6: AMPOL | G6: =IF( OR(ISBLANK(Monthly_Table[[#This Row],[Total_time_worked]]), ISBLANK(Monthly_Table[[#This Row],[organization ]])), "Enter time and organization", IF( AND( ISNUMBER(Monthly_Table[[#This Row],[Total_time_worked]]), ISNUMBER(VLOOKUP(Monthly_Table[[#This Row],[organization ]], Rate_Table[], 3, FALSE)) ), ROUND(Monthly_Table[[#This Row],[Total_time_worked]] * VLOOKUP(Monthly_Table[[#This Row],[organization ]], Rate_Table[], 3, FALSE), 2), "Error: Invalid input or missing rate" ) ) -> 263.5 | L6: AMPOL_SPL | M6: Teammember | N6: 35 | O6: =IFERROR(SUMIFS(Monthly_Table[Money_Earned], Monthly_Table[[organization ]], Rate_Table[[#This Row],[Organization]]), 0) -> 595
A7: 45660 | B7: =TEXT(Monthly_Table[[#This Row],[Date]],"ddd") -> Fri | C7: 0.75 | D7: 0.95833333 | E7: =IF( AND(ISBLANK(Monthly_Table[[#This Row],[start_time]]), ISBLANK(Monthly_Table[[#This Row],[end_time]])), "Enter time", IF( AND(ISNUMBER(Monthly_Table[[#This Row],[start_time]]), ISNUMBER(Monthly_Table[[#This Row],[end_time]])), IF( Monthly_Table[[#This Row],[end_time]] >= Monthly_Table[[#This Row],[start_time]], (Monthly_Table[[#This Row],[end_time]] - Monthly_Table[[#This Row],[start_time]]) * 24, "Error: End time before start" ), "Error: Invalid time format" ) ) -> 5 | F7: COLES | G7: =IF( OR(ISBLANK(Monthly_Table[[#This Row],[Total_time_worked]]), ISBLANK(Monthly_Table[[#This Row],[organization ]])), "Enter time and organization", IF( AND( ISNUMBER(Monthly_Table[[#This Row],[Total_time_worked]]), ISNUMBER(VLOOKUP(Monthly_Table[[#This Row],[organization ]], Rate_Table[], 3, FALSE)) ), ROUND(Monthly_Table[[#This Row],[Total_time_worked]] * VLOOKUP(Monthly_Table[[#This Row],[organization ]], Rate_Table[], 3, FALSE), 2), "Error: Invalid input or missing rate" ) ) -> 125
A8: 45661 | B8: =TEXT(Monthly_Table[[#This Row],[Date]],"ddd") -> Sat | C8: 0.375 | D8: 0.72916667 | E8: =IF( AND(ISBLANK(Monthly_Table[[#This Row],[start_time]]), ISBLANK(Monthly_Table[[#This Row],[end_time]])), "Enter time", IF( AND(ISNUMBER(Monthly_Table[[#This Row],[start_time]]), ISNUMBER(Monthly_Table[[#This Row],[end_time]])), IF( Monthly_Table[[#This Row],[end_time]] >= Monthly_Table[[#This Row],[start_time]], (Monthly_Table[[#This Row],[end_time]] - Monthly_Table[[#This Row],[start_time]]) * 24, "Error: End time before start" ), "Error: Invalid time format" ) ) -> 8.5 | F8: AMPOL_SPL | G8: =IF( OR(ISBLANK(Monthly_Table[[#This Row],[Total_time_worked]]), ISBLANK(Monthly_Table[[#This Row],[organization ]])), "Enter time and organization", IF( AND( ISNUMBER(Monthly_Table[[#This Row],[Total_time_worked]]), ISNUMBER(VLOOKUP(Monthly_Table[[#This Row],[organization ]], Rate_Table[], 3, FALSE)) ), ROUND(Monthly_Table[[#This Row],[Total_time_worked]] * VLOOKUP(Monthly_Table[[#This Row],[organization ]], Rate_Table[], 3, FALSE), 2), "Error: Invalid input or missing rate" ) ) -> 297.5
A9: 45661 | B9: =TEXT(Monthly_Table[[#This Row],[Date]],"ddd") -> Sat | C9: 0.75 | D9: 0.95833333 | E9: =IF( AND(ISBLANK(Monthly_Table[[#This Row],[start_time]]), ISBLANK(Monthly_Table[[#This Row],[end_time]])), "Enter time", IF( AND(ISNUMBER(Monthly_Table[[#This Row],[start_time]]), ISNUMBER(Monthly_Table[[#This Row],[end_time]])), IF( Monthly_Table[[#This Row],[end_time]] >= Monthly_Table[[#This Row],[start_time]], (Monthly_Table[[#This Row],[end_time]] - Monthly_Table[[#This Row],[start_time]]) * 24, "Error: End time before start" ), "Error: Invalid time format" ) ) -> 5 | F9: COLES_SPL | G9: =IF( OR(ISBLANK(Monthly_Table[[#This Row],[Total_time_worked]]), ISBLANK(Monthly_Table[[#This Row],[organization ]])), "Enter time and organization", IF( AND( ISNUMBER(Monthly_Table[[#This Row],[Total_time_worked]]), ISNUMBER(VLOOKUP(Monthly_Table[[#This Row],[organization ]], Rate_Table[], 3, FALSE)) ), ROUND(Monthly_Table[[#This Row],[Total_time_worked]] * VLOOKUP(Monthly_Table[[#This Row],[organization ]], Rate_Table[], 3, FALSE), 2), "Error: Invalid input or missing rate" ) ) -> 140
A10: 45662 | B10: =TEXT(Monthly_Table[[#This Row],[Date]],"ddd") -> Sun | C10: 0.375 | D10: 0.72916667 | E10: =IF( AND(ISBLANK(Monthly_Table[[#This Row],[start_time]]), ISBLANK(Monthly_Table[[#This Row],[end_time]])), "Enter time", IF( AND(ISNUMBER(Monthly_Table[[#This Row],[start_time]]), ISNUMBER(Monthly_Table[[#This Row],[end_time]])), IF( Monthly_Table[[#This Row],[end_time]] >= Monthly_Table[[#This Row],[start_time]], (Monthly_Table[[#This Row],[end_time]] - Monthly_Table[[#This Row],[start_time]]) * 24, "Error: End time before start" ), "Error: Invalid time format" ) ) -> 8.5 | F10: AMPOL_SPL | G10: =IF( OR(ISBLANK(Monthly_Table[[#This Row],[Total_time_worked]]), ISBLANK(Monthly_Table[[#This Row],[organization ]])), "Enter time and organization", IF( AND( ISNUMBER(Monthly_Table[[#This Row],[Total_time_worked]]), ISNUMBER(VLOOKUP(Monthly_Table[[#This Row],[organization ]], Rate_Table[], 3, FALSE)) ), ROUND(Monthly_Table[[#This Row],[Total_time_worked]] * VLOOKUP(Monthly_Table[[#This Row],[organization ]], Rate_Table[], 3, FALSE), 2), "Error: Invalid input or missing rate" ) ) -> 297.5
A11: 45662 | B11: =TEXT(Monthly_Table[[#This Row],[Date]],"ddd") -> Sun | C11: 0.75 | D11: 0.95833333 | E11: =IF( AND(ISBLANK(Monthly_Table[[#This Row],[start_time]]), ISBLANK(Monthly_Table[[#This Row],[end_time]])), "Enter time", IF( AND(ISNUMBER(Monthly_Table[[#This Row],[start_time]]), ISNUMBER(Monthly_Table[[#This Row],[end_time]])), IF( Monthly_Table[[#This Row],[end_time]] >= Monthly_Table[[#This Row],[start_time]], (Monthly_Table[[#This Row],[end_time]] - Monthly_Table[[#This Row],[start_time]]) * 24, "Error: End time before start" ), "Error: Invalid time format" ) ) -> 5 | F11: COLES_SPL | G11: =IF( OR(ISBLANK(Monthly_Table[[#This Row],[Total_time_worked]]), ISBLANK(Monthly_Table[[#This Row],[organization ]])), "Enter time and organization", IF( AND( ISNUMBER(Monthly_Table[[#This Row],[Total_time_worked]]), ISNUMBER(VLOOKUP(Monthly_Table[[#This Row],[organization ]], Rate_Table[], 3, FALSE)) ), ROUND(Monthly_Table[[#This Row],[Total_time_worked]] * VLOOKUP(Monthly_Table[[#This Row],[organization ]], Rate_Table[], 3, FALSE), 2), "Error: Invalid input or missing rate" ) ) -> 140
A12: 45663 | B12: =TEXT(Monthly_Table[[#This Row],[Date]],"ddd") -> Mon | C12: 0.375 | D12: 0.72916667 | E12: =IF( AND(ISBLANK(Monthly_Table[[#This Row],[start_time]]), ISBLANK(Monthly_Table[[#This Row],[end_time]])), "Enter time", IF( AND(ISNUMBER(Monthly_Table[[#This Row],[start_time]]), ISNUMBER(Monthly_Table[[#This Row],[end_time]])), IF( Monthly_Table[[#This Row],[end_time]] >= Monthly_Table[[#This Row],[start_time]], (Monthly_Table[[#This Row],[end_time]] - Monthly_Table[[#This Row],[start_time]]) * 24, "Error: End time before start" ), "Error: Invalid time format" ) ) -> 8.5 | F12: AMPOL | G12: =IF( OR(ISBLANK(Monthly_Table[[#This Row],[Total_time_worked]]), ISBLANK(Monthly_Table[[#This Row],[organization ]])), "Enter time and organization", IF( AND( ISNUMBER(Monthly_Table[[#This Row],[Total_time_worked]]), ISNUMBER(VLOOKUP(Monthly_Table[[#This Row],[organization ]], Rate_Table[], 3, FALSE)) ), ROUND(Monthly_Table[[#This Row],[Total_time_worked]] * VLOOKUP(Monthly_Table[[#This Row],[organization ]], Rate_Table[], 3, FALSE), 2), "Error: Invalid input or missing rate" ) ) -> 263.5
A13: 45663 | B13: =TEXT(Monthly_Table[[#This Row],[Date]],"ddd") -> Mon | C13: 0.75 | D13: 0.95833333 | E13: =IF( AND(ISBLANK(Monthly_Table[[#This Row],[start_time]]), ISBLANK(Monthly_Table[[#This Row],[end_time]])), "Enter time", IF( AND(ISNUMBER(Monthly_Table[[#This Row],[start_time]]), ISNUMBER(Monthly_Table[[#This Row],[end_time]])), IF( Monthly_Table[[#This Row],[end_time]] >= Monthly_Table[[#This Row],[start_time]], (Monthly_Table[[#This Row],[end_time]] - Monthly_Table[[#This Row],[start_time]]) * 24, "Error: End time before start" ), "Error: Invalid time format" ) ) -> 5 | F13: COLES | G13: =IF( OR(ISBLANK(Monthly_Table[[#This Row],[Total_time_worked]]), ISBLANK(Monthly_Table[[#This Row],[organization ]])), "Enter time and organization", IF( AND( ISNUMBER(Monthly_Table[[#This Row],[Total_time_worked]]), ISNUMBER(VLOOKUP(Monthly_Table[[#This Row],[organization ]], Rate_Table[], 3, FALSE)) ), ROUND(Monthly_Table[[#This Row],[Total_time_worked]] * VLOOKUP(Monthly_Table[[#This Row],[organization ]], Rate_Table[], 3, FALSE), 2), "Error: Invalid input or missing rate" ) ) -> 125
A14: 45664 | B14: =TEXT(Monthly_Table[[#This Row],[Date]],"ddd") -> Tue | C14: 0.375 | D14: 0.72916667 | E14: =IF( AND(ISBLANK(Monthly_Table[[#This Row],[start_time]]), ISBLANK(Monthly_Table[[#This Row],[end_time]])), "Enter time", IF( AND(ISNUMBER(Monthly_Table[[#This Row],[start_time]]), ISNUMBER(Monthly_Table[[#This Row],[end_time]])), IF( Monthly_Table[[#This Row],[end_time]] >= Monthly_Table[[#This Row],[start_time]], (Monthly_Table[[#This Row],[end_time]] - Monthly_Table[[#This Row],[start_time]]) * 24, "Error: End time before start" ), "Error: Invalid time format" ) ) -> 8.5 | F14: AMPOL | G14: =IF( OR(ISBLANK(Monthly_Table[[#This Row],[Total_time_worked]]), ISBLANK(Monthly_Table[[#This Row],[organization ]])), "Enter time and organization", IF( AND( ISNUMBER(Monthly_Table[[#This Row],[Total_time_worked]]), ISNUMBER(VLOOKUP(Monthly_Table[[#This Row],[organization ]], Rate_Table[], 3, FALSE)) ), ROUND(Monthly_Table[[#This Row],[Total_time_worked]] * VLOOKUP(Monthly_Table[[#This Row],[organization ]], Rate_Table[], 3, FALSE), 2), "Error: Invalid input or missing rate" ) ) -> 263.5
A15: 45664 | B15: =TEXT(Monthly_Table[[#This Row],[Date]],"ddd") -> Tue | C15: 0.75 | D15: 0.95833333 | E15: =IF( AND(ISBLANK(Monthly_Table[[#This Row],[start_time]]), ISBLANK(Monthly_Table[[#This Row],[end_time]])), "Enter time", IF( AND(ISNUMBER(Monthly_Table[[#This Row],[start_time]]), ISNUMBER(Monthly_Table[[#This Row],[end_time]])), IF( Monthly_Table[[#This Row],[end_time]] >= Monthly_Table[[#This Row],[start_time]], (Monthly_Table[[#This Row],[end_time]] - Monthly_Table[[#This Row],[start_time]]) * 24, "Error: End time before start" ), "Error: Invalid time format" ) ) -> 5 | F15: COLES | G15: =IF( OR(ISBLANK(Monthly_Table[[#This Row],[Total_time_worked]]), ISBLANK(Monthly_Table[[#This Row],[organization ]])), "Enter time and organization", IF( AND( ISNUMBER(Monthly_Table[[#This Row],[Total_time_worked]]), ISNUMBER(VLOOKUP(Monthly_Table[[#This Row],[organization ]], Rate_Table[], 3, FALSE)) ), ROUND(Monthly_Table[[#This Row],[Total_time_worked]] * VLOOKUP(Monthly_Table[[#This Row],[organization ]], Rate_Table[], 3, FALSE), 2), "Error: Invalid input or missing rate" ) ) -> 125

Sheet Transactions
A1: Date | B1: Day | C1: Category | D1: Type (Income/Expense) | E1: Account | F1: Amount | G1: Notes | H1: Tags | I1: Balance
A2: 45658 | B2: =IF(ISNUMBER(Txn_table[[#This Row],[Date]]),(TEXT(Txn_table[[#This Row],[Date]],"ddd")),"Date Required!") -> Wed | C2: Salary | D2: Income | E2: Bank | F2: 625 | G2: Jan Salary coles | H2: Work | I2: =SUMIFS( Txn_table[Amount], Txn_table[Type (Income/Expense)], "Income", Txn_table[Date], "<=" & Txn_table[[#This Row],[Date]] ) - SUMIFS( Txn_table[Amount], Txn_table[Type (Income/Expense)], "Expense", Txn_table[Date], "<=" & Txn_table[[#This Row],[Date]] ) -> 1767.5
A3: 45658 | B3: =IF(ISNUMBER(Txn_table[[#This Row],[Date]]),(TEXT(Txn_table[[#This Row],[Date]],"ddd")),"Date Required!") -> Wed | C3: Bonus | D3: Income | E3: Bank | F3: 100 | G3: Bonus new year 2025 | H3: Work | I3: =SUMIFS( Txn_table[Amount], Txn_table[Type (Income/Expense)], "Income", Txn_table[Date], "<=" & Txn_table[[#This Row],[Date]] ) - SUMIFS( Txn_table[Amount], Txn_table[Type (Income/Expense)], "Expense", Txn_table[Date], "<=" & Txn_table[[#This Row],[Date]] ) -> 1767.5
A4: 45658 | B4: =IF(ISNUMBER(Txn_table[[#This Row],[Date]]),(TEXT(Txn_table[[#This Row],[Date]],"ddd")),"Date Required!") -> Wed | C4: Salary | D4: Income | E4: Bank | F4: 1317.5 | G4: Jan Salary Ampol | H4: Work | I4: =SUMIFS( Txn_table[Amount], Txn_table[Type (Income/Expense)], "Income", Txn_table[Date], "<=" & Txn_table[[#This Row],[Date]] ) - SUMIFS( Txn_table[Amount], Txn_table[Type (Income/Expense)], "Expense", Txn_table[Date], "<=" & Txn_table[[#This Row],[Date]] ) -> 1767.5
A5: 45658 | B5: =IF(ISNUMBER(Txn_table[[#This Row],[Date]]),(TEXT(Txn_table[[#This Row],[Date]],"ddd")),"Date Required!") -> Wed | C5: Bonus | D5: Income | E5: Bank | F5: 100 | G5: Bonus new year 2025 | H5: Work | I5: =SUMIFS( Txn_table[Amount], Txn_table[Type (Income/Expense)], "Income", Txn_table[Date], "<=" & Txn_table[[#This Row],[Date]] ) - SUMIFS( Txn_table[Amount], Txn_table[Type (Income/Expense)], "Expense", Txn_table[Date], "<=" & Txn_table[[#This Row],[Date]] ) -> 1767.5
A6: 45658 | B6: =IF(ISNUMBER(Txn_table[[#This Row],[Date]]),(TEXT(Txn_table[[#This Row],[Date]],"ddd")),"Date Required!") -> Wed | C6: Rent | D6: Expense | E6: Bank | F6: 250 | G6: January 1 Rent | H6: Fixed | I6: =SUMIFS( Txn_table[Amount], Txn_table[Type (Income/Expense)], "Income", Txn_table[Date], "<=" & Txn_table[[#This Row],[Date]] ) - SUMIFS( Txn_table[Amount], Txn_table[Type (Income/Expense)], "Expense", Txn_table[Date], "<=" & Txn_table[[#This Row],[Date]] ) -> 1767.5
A7: 45658 | B7: =IF(ISNUMBER(Txn_table[[#This Row],[Date]]),(TEXT(Txn_table[[#This Row],[Date]],"ddd")),"Date Required!") -> Wed | C7: Food | D7: Expense | E7: Credit | F7: 50 | G7: Groceries | H7: Variable | I7: =SUMIFS( Txn_table[Amount], Txn_table[Type (Income/Expense)], "Income", Txn_table[Date], "<=" & Txn_table[[#This Row],[Date]] ) - SUMIFS( Txn_table[Amount], Txn_table[Type (Income/Expense)], "Expense", Txn_table[Date], "<=" & Txn_table[[#This Row],[Date]] ) -> 1767.5
A8: 45658 | B8: =IF(ISNUMBER(Txn_table[[#This Row],[Date]]),(TEXT(Txn_table[[#This Row],[Date]],"ddd")),"Date Required!") -> Wed | C8: Travel | D8: Expense | E8: Credit | F8: 20 | G8: bus | H8: Work | I8: =SUMIFS( Txn_table[Amount], Txn_table[Type (Income/Expense)], "Income", Txn_table[Date], "<=" & Txn_table[[#This Row],[Date]] ) - SUMIFS( Txn_table[Amount], Txn_table[Type (Income/Expense)], "Expense", Txn_table[Date], "<=" & Txn_table[[#This Row],[Date]] ) -> 1767.5
A9: 45658 | B9: =IF(ISNUMBER(Txn_table[[#This Row],[Date]]),(TEXT(Txn_table[[#This Row],[Date]],"ddd")),"Date Required!") -> Wed | C9: Mobile Bills | D9: Expense | E9: Credit | F9: 55 | G9: Mobile Bills | H9: Fixed | I9: =SUMIFS( Txn_table[Amount], Txn_table[Type (Income/Expense)], "Income", Txn_table[Date], "<=" & Txn_table[[#This Row],[Date]] ) - SUMIFS( Txn_table[Amount], Txn_table[Type (Income/Expense)], "Expense", Txn_table[Date], "<=" & Txn_table[[#This Row],[Date]] ) -> 1767.5
A10: 45659 | B10: =IF(ISNUMBER(Txn_table[[#This Row],[Date]]),(TEXT(Txn_table[[#This Row],[Date]],"ddd")),"Date Required!") -> Thu | C10: Food | D10: Expense | E10: Credit | F10: 25 | G10: Food | H10: Variable | I10: =SUMIFS( Txn_table[Amount], Txn_table[Type (Income/Expense)], "Income", Txn_table[Date], "<=" & Txn_table[[#This Row],[Date]] ) - SUMIFS( Txn_table[Amount], Txn_table[Type (Income/Expense)], "Expense", Txn_table[Date], "<=" & Txn_table[[#This Row],[Date]] ) -> 1722.5
A11: 45659 | B11: =IF(ISNUMBER(Txn_table[[#This Row],[Date]]),(TEXT(Txn_table[[#This Row],[Date]],"ddd")),"Date Required!") -> Thu | C11: Travel | D11: Expense | E11: Credit | F11: 20 | G11: Travel | H11: Work | I11: =SUMIFS( Txn_table[Amount], Txn_table[Type (Income/Expense)], "Income", Txn_table[Date], "<=" & Txn_table[[#This Row],[Date]] ) - SUMIFS( Txn_table[Amount], Txn_table[Type (Income/Expense)], "Expense", Txn_table[Date], "<=" & Txn_table[[#This Row],[Date]] ) -> 1722.5
A12: 45660 | B12: =IF(ISNUMBER(Txn_table[[#This Row],[Date]]),(TEXT(Txn_table[[#This Row],[Date]],"ddd")),"Date Required!") -> Fri | C12: Food | D12: Expense | E12: Credit | F12: 35 | G12: Food | H12: Variable | I12: =SUMIFS( Txn_table[Amount], Txn_table[Type (Income/Expense)], "Income", Txn_table[Date], "<=" & Txn_table[[#This Row],[Date]] ) - SUMIFS( Txn_table[Amount], Txn_table[Type (Income/Expense)], "Expense", Txn_table[Date], "<=" & Txn_table[[#This Row],[Date]] ) -> 1667.5
A13: 45660 | B13: =IF(ISNUMBER(Txn_table[[#This Row],[Date]]),(TEXT(Txn_table[[#This Row],[Date]],"ddd")),"Date Required!") -> Fri | C13: Travel | D13: Expense | E13: Credit | F13: 20 | G13: Travel | H13: Work | I13: =SUMIFS( Txn_table[Amount], Txn_table[Type (Income/Expense)], "Income", Txn_table[Date], "<=" & Txn_table[[#This Row],[Date]] ) - SUMIFS( Txn_table[Amount], Txn_table[Type (Income/Expense)], "Expense", Txn_table[Date], "<=" & Txn_table[[#This Row],[Date]] ) -> 1667.5
... A21: 45664 | B21: =IF(ISNUMBER(Txn_table[[#This Row],[Date]]),(TEXT(Txn_table[[#This Row],[Date]],"ddd")),"Date Required!") -> Tue | C21: Travel | D21: Expense | E21: Credit | F21: 20 | G21: Travel | H21: Work | I21: =SUMIFS( Txn_table[Amount], Txn_table[Type (Income/Expense)], "Income", Txn_table[Date], "<=" & Txn_table[[#This Row],[Date]] ) - SUMIFS( Txn_table[Amount], Txn_table[Type (Income/Expense)], "Expense", Txn_table[Date], "<=" & Txn_table[[#This Row],[Date]] ) -> 1481.5
B22: =IF(ISNUMBER(Txn_table[[#This Row],[Date]]),(TEXT(Txn_table[[#This Row],[Date]],"ddd")),"Date Required!") -> Date Required! | I22: =SUMIFS( Txn_table[Amount], Txn_table[Type (Income/Expense)], "Income", Txn_table[Date], "<=" & Txn_table[[#This Row],[Date]] ) - SUMIFS( Txn_table[Amount], Txn_table[Type (Income/Expense)], "Expense", Txn_table[Date], "<=" & Txn_table[[#This Row],[Date]] ) -> 0
B23: =IF(ISNUMBER(Txn_table[[#This Row],[Date]]),(TEXT(Txn_table[[#This Row],[Date]],"ddd")),"Date Required!") -> Date Required! | I23: =SUMIFS( Txn_table[Amount], Txn_table[Type (Income/Expense)], "Income", Txn_table[Date], "<=" & Txn_table[[#This Row],[Date]] ) - SUMIFS( Txn_table[Amount], Txn_table[Type (Income/Expense)], "Expense", Txn_table[Date], "<=" & Txn_table[[#This Row],[Date]] ) -> 0
B24: =IF(ISNUMBER(Txn_table[[#This Row],[Date]]),(TEXT(Txn_table[[#This Row],[Date]],"ddd")),"Date Required!") -> Date Required! | I24: =SUMIFS( Txn_table[Amount], Txn_table[Type (Income/Expense)], "Income", Txn_table[Date], "<=" & Txn_table[[#This Row],[Date]] ) - SUMIFS( Txn_table[Amount], Txn_table[Type (Income/Expense)], "Expense", Txn_table[Date], "<=" & Txn_table[[#This Row],[Date]] ) -> 0

Sheet Summary
D1: Budget Tracking Dashboard
A3: Income | B3: Amount
A4: Salary | B4: =SUM(Rate_Table[Total_Earned]) -> 2817.5 | C4: =_xlfn.FORMULATEXT(B4) -> =SUM(Rate_Table[Total_Earned])
A5: tax (20%) | B5: =-15%*B4 -> -422.625 | C5: =_xlfn.FORMULATEXT(B5) -> =-15%*B4
A6: Super | B6: =-11%*B4 -> -309.925 | C6: =_xlfn.FORMULATEXT(B6) -> =-11%*B4
A7: Insurance | B7: =-8%*B4 -> -225.4 | C7: =_xlfn.FORMULATEXT(B7) -> =-8%*B4
A8: Bonus | B8: =5%*B4 -> 140.875 | C8: =_xlfn.FORMULATEXT(B8) -> =5%*B4
A9: Net Income | B9: =SUM(B4:B8) -> 2000.425 | C9: =_xlfn.FORMULATEXT(B9) -> =SUM(B4:B8)
A11: Expense | B11: Amount | C11: Formulated Answers
A12: Expense | B12: =VALUE(Table11[[#This Row],[Formulated Answers]]) -> 661 | C12: =VALUE(SUM(C13:C17)) -> 661
A13: Rent | B13: =VALUE(Table11[[#This Row],[Formulated Answers]]) -> 250 | C13: =IFERROR(VALUE(SUMIFS(Txn_table[Amount], Txn_table[Category], Summary!A13)), 0) -> 250
A14: Food | B14: =VALUE(Table11[[#This Row],[Formulated Answers]]) -> 216 | C14: =IFERROR(VALUE(SUMIFS(Txn_table[Amount], Txn_table[Category], Summary!A14)), 0) -> 216
A15: Travel | B15: =VALUE(Table11[[#This Row],[Formulated Answers]]) -> 100 | C15: =IFERROR(VALUE(SUMIFS(Txn_table[Amount], Txn_table[Category], Summary!A15)), 0) -> 100
A16: Mobile Bills | B16: =VALUE(Table11[[#This Row],[Formulated Answers]]) -> 55 | C16: =IFERROR(VALUE(SUMIFS(Txn_table[Amount], Txn_table[Category], Summary!A16)), 0) -> 55
A17: Car Petrol | B17: =VALUE(Table11[[#This Row],[Formulated Answers]]) -> 40 | C17: =IFERROR(VALUE(SUMIFS(Txn_table[Amount], Txn_table[Category], Summary!A17)), 0) -> 40
A19: Net Profit | B19: =B9-B12 -> 1339.425
A20: % Saving | B20: =(1-B12/B19) -> 0.50650466
A21: %Expenses | B21: =1-B20 -> 0.49349534
A23: KPI
A24: Saving Rate | B24: =(net_profit/net_income) -> 0.66957022
A25: Burn Rate | B25: =(net_expense/net_income) -> 0.33042978
A26: Net CashFlow | B26: =net_income-net_expense -> 1339.425

Sheet Saving Goals
B2: Budgeting
B3: Category | C3: Budget | D3: Actual | E3: Variance | F3: %_Variance | H3: Note:
B4: Rent | C4: 250 | D4: =VALUE(Summary!B13) -> 250 | E4: =Budget[[#This Row],[Actual]]-Budget[[#This Row],[Budget]] -> 0 | F4: =Budget[[#This Row],[Variance]]/Budget[[#This Row],[Budget]] -> 0 | H4: Variance = C2 - B2
B5: Food | C5: 250 | D5: =VALUE(Summary!B14) -> 216 | E5: =Budget[[#This Row],[Actual]]-Budget[[#This Row],[Budget]] -> -34 | F5: =Budget[[#This Row],[Variance]]/Budget[[#This Row],[Budget]] -> -0.136 | H5: %_Variance = D2 / B2
B6: Travel | C6: 110 | D6: =VALUE(Summary!B15) -> 100 | E6: =Budget[[#This Row],[Actual]]-Budget[[#This Row],[Budget]] -> -10 | F6: =Budget[[#This Row],[Variance]]/Budget[[#This Row],[Budget]] -> -0.090909091
B7: Mobile Bills | C7: 55 | D7: =VALUE(Summary!B16) -> 55 | E7: =Budget[[#This Row],[Actual]]-Budget[[#This Row],[Budget]] -> 0 | F7: =Budget[[#This Row],[Variance]]/Budget[[#This Row],[Budget]] -> 0
B8: Car Petrol | C8: 30 | D8: =VALUE(Summary!B17) -> 40 | E8: =Budget[[#This Row],[Actual]]-Budget[[#This Row],[Budget]] -> 10 | F8: =Budget[[#This Row],[Variance]]/Budget[[#This Row],[Budget]] -> 0.33333333
B10: Goal Tracker
B11: Goal | C11: Target Amount | D11: Current Savings | E11: % Achieved | F11: $ to go | G11: Priority | H11: DeadLine | I11: Total Month Left | J11: Monthly Goal
B12: Emergency Fund | C12: 10000 | D12: =IF(ISNUMBER(Goal_todo[[#This Row],[Target Amount]]),VALUE(net_profit),) -> 1339.425 | E12: =IF(ISNUMBER(Goal_todo[[#This Row],[Target Amount]]),VALUE(IF(AND(ISNUMBER(Goal_todo[[#This Row],[Target Amount]]), ISNUMBER(Goal_todo[[#This Row],[Current Savings]]), Goal_todo[[#This Row],[Target Amount]]>0), ROUND(Goal_todo[[#This Row],[Current Savings]]/Goal_todo[[#This Row],[Target Amount]], 4), "")),) -> 0.1339 | F12: =IF(AND(ISNUMBER(Goal_todo[[#This Row],[Target Amount]]), ISNUMBER(Goal_todo[[#This Row],[Current Savings]])), MAX(Goal_todo[[#This Row],[Target Amount]] - Goal_todo[[#This Row],[Current Savings]], 0), "") -> 8660.575 | G12: High | H12: 45992 | I12: =IF(ISNUMBER(Goal_todo[[#This Row],[DeadLine]]),DATEDIF(TODAY(), Goal_todo[[#This Row],[DeadLine]], "m"),) -> #NUM! | J12: =IF(Goal_todo[[#This Row],[Current Savings]]<Goal_todo[[#This Row],[Target Amount]], ROUND((Goal_todo[[#This Row],[Target Amount]]-Goal_todo[[#This Row],[Current Savings]])/DATEDIF(TODAY(),Goal_todo[[#This Row],[DeadLine]],"m"), 2), 0) -> #NUM!
B13: Car Emergency Fund | C13: 8000 | D13: =IF(ISNUMBER(Goal_todo[[#This Row],[Target Amount]]),VALUE(net_profit),) -> 1339.425 | E13: =IF(ISNUMBER(Goal_todo[[#This Row],[Target Amount]]),VALUE(IF(AND(ISNUMBER(Goal_todo[[#This Row],[Target Amount]]), ISNUMBER(Goal_todo[[#This Row],[Current Savings]]), Goal_todo[[#This Row],[Target Amount]]>0), ROUND(Goal_todo[[#This Row],[Current Savings]]/Goal_todo[[#This Row],[Target Amount]], 4), "")),) -> 0.1674 | F13: =IF(AND(ISNUMBER(Goal_todo[[#This Row],[Target Amount]]), ISNUMBER(Goal_todo[[#This Row],[Current Savings]])), MAX(Goal_todo[[#This Row],[Target Amount]] - Goal_todo[[#This Row],[Current Savings]], 0), "") -> 6660.575 | G13: Medium | H13: 46357 | I13: =IF(ISNUMBER(Goal_todo[[#This Row],[DeadLine]]),DATEDIF(TODAY(), Goal_todo[[#This Row],[DeadLine]], "m"),) -> 10 | J13: =IF(Goal_todo[[#This Row],[Current Savings]]<Goal_todo[[#This Row],[Target Amount]], ROUND((Goal_todo[[#This Row],[Target Amount]]-Goal_todo[[#This Row],[Current Savings]])/DATEDIF(TODAY(),Goal_todo[[#This Row],[DeadLine]],"m"), 2), 0) -> 666.06
B14: Travel | C14: 5000 | D14: =IF(ISNUMBER(Goal_todo[[#This Row],[Target Amount]]),VALUE(net_profit),) -> 1339.425 | E14: =IF(ISNUMBER(Goal_todo[[#This Row],[Target Amount]]),VALUE(IF(AND(ISNUMBER(Goal_todo[[#This Row],[Target Amount]]), ISNUMBER(Goal_todo[[#This Row],[Current Savings]]), Goal_todo[[#This Row],[Target Amount]]>0), ROUND(Goal_todo[[#This Row],[Current Savings]]/Goal_todo[[#This Row],[Target Amount]], 4), "")),) -> 0.2679 | F14: =IF(AND(ISNUMBER(Goal_todo[[#This Row],[Target Amount]]), ISNUMBER(Goal_todo[[#This Row],[Current Savings]])), MAX(Goal_todo[[#This Row],[Target Amount]] - Goal_todo[[#This Row],[Current Savings]], 0), "") -> 3660.575 | G14: Medium | H14: 49644 | I14: =IF(ISNUMBER(Goal_todo[[#This Row],[DeadLine]]),DATEDIF(TODAY(), Goal_todo[[#This Row],[DeadLine]], "m"),) -> 118 | J14: =IF(Goal_todo[[#This Row],[Current Savings]]<Goal_todo[[#This Row],[Target Amount]], ROUND((Goal_todo[[#This Row],[Target Amount]]-Goal_todo[[#This Row],[Current Savings]])/DATEDIF(TODAY(),Goal_todo[[#This Row],[DeadLine]],"m"), 2), 0) -> 31.02
B15: House Deposit | C15: 100000 | D15: =IF(ISNUMBER(Goal_todo[[#This Row],[Target Amount]]),VALUE(net_profit),) -> 1339.425 | E15: =IF(ISNUMBER(Goal_todo[[#This Row],[Target Amount]]),VALUE(IF(AND(ISNUMBER(Goal_todo[[#This Row],[Target Amount]]), ISNUMBER(Goal_todo[[#This Row],[Current Savings]]), Goal_todo[[#This Row],[Target Amount]]>0), ROUND(Goal_todo[[#This Row],[Current Savings]]/Goal_todo[[#This Row],[Target Amount]], 4), "")),) -> 0.0134 | F15: =IF(AND(ISNUMBER(Goal_todo[[#This Row],[Target Amount]]), ISNUMBER(Goal_todo[[#This Row],[Current Savings]])), MAX(Goal_todo[[#This Row],[Target Amount]] - Goal_todo[[#This Row],[Current Savings]], 0), "") -> 98660.575 | G15: High | H15: 53144 | I15: =IF(ISNUMBER(Goal_todo[[#This Row],[DeadLine]]),DATEDIF(TODAY(), Goal_todo[[#This Row],[DeadLine]], "m"),) -> 233 | J15: =IF(Goal_todo[[#This Row],[Current Savings]]<Goal_todo[[#This Row],[Target Amount]], ROUND((Goal_todo[[#This Row],[Target Amount]]-Goal_todo[[#This Row],[Current Savings]])/DATEDIF(TODAY(),Goal_todo[[#This Row],[DeadLine]],"m"), 2), 0) -> 423.44
B16: Retirement | C16: 250000 | D16: =IF(ISNUMBER(Goal_todo[[#This Row],[Target Amount]]),VALUE(net_profit),) -> 1339.425 | E16: =IF(ISNUMBER(Goal_todo[[#This Row],[Target Amount]]),VALUE(IF(AND(ISNUMBER(Goal_todo[[#This Row],[Target Amount]]), ISNUMBER(Goal_todo[[#This Row],[Current Savings]]), Goal_todo[[#This Row],[Target Amount]]>0), ROUND(Goal_todo[[#This Row],[Current Savings]]/Goal_todo[[#This Row],[Target Amount]], 4), "")),) -> 0.0054 | F16: =IF(AND(ISNUMBER(Goal_todo[[#This Row],[Target Amount]]), ISNUMBER(Goal_todo[[#This Row],[Current Savings]])), MAX(Goal_todo[[#This Row],[Target Amount]] - Goal_todo[[#This Row],[Current Savings]], 0), "") -> 248660.58 | G16: Long Term | H16: 71225 | I16: =IF(ISNUMBER(Goal_todo[[#This Row],[DeadLine]]),DATEDIF(TODAY(), Goal_todo[[#This Row],[DeadLine]], "m"),) -> 827 | J16: =IF(Goal_todo[[#This Row],[Current Savings]]<Goal_todo[[#This Row],[Target Amount]], ROUND((Goal_todo[[#This Row],[Target Amount]]-Goal_todo[[#This Row],[Current Savings]])/DATEDIF(TODAY(),Goal_todo[[#This Row],[DeadLine]],"m"), 2), 0) -> 300.68
D17: =IF(ISNUMBER(Goal_todo[[#This Row],[Target Amount]]),VALUE(net_profit),) -> 0 | E17: =IF(ISNUMBER(Goal_todo[[#This Row],[Target Amount]]),VALUE(IF(AND(ISNUMBER(Goal_todo[[#This Row],[Target Amount]]), ISNUMBER(Goal_todo[[#This Row],[Current Savings]]), Goal_todo[[#This Row],[Target Amount]]>0), ROUND(Goal_todo[[#This Row],[Current Savings]]/Goal_todo[[#This Row],[Target Amount]], 4), "")),) -> 0 | F17: =IF(AND(ISNUMBER(Goal_todo[[#This Row],[Target Amount]]), ISNUMBER(Goal_todo[[#This Row],[Current Savings]])), MAX(Goal_todo[[#This Row],[Target Amount]] - Goal_todo[[#This Row],[Current Savings]], 0), "") | I17: =IF(ISNUMBER(Goal_todo[[#This Row],[DeadLine]]),DATEDIF(TODAY(), Goal_todo[[#This Row],[DeadLine]], "m"),) -> 0 | J17: =IF(Goal_todo[[#This Row],[Current Savings]]<Goal_todo[[#This Row],[Target Amount]], ROUND((Goal_todo[[#This Row],[Target Amount]]-Goal_todo[[#This Row],[Current Savings]])/DATEDIF(TODAY(),Goal_todo[[#This Row],[DeadLine]],"m"), 2), 0) -> 0
B20: Goal Achieved
B21: Date | C21: Goal | D21: Amount
B22: 45658 | C22: Mobile | D22: 1300

Sheet Dashboard
B2: Budget Tracking Dashboard
B4: Name | C4: John Doe
B5: Age | C5: 25
B6: Occupation | C6: Team Member
B8: Assets | C8: Amount
B9: Bank Balance | C9: =net_profit -> 1339.425
B10: Property Value | C10: 0
B11: Total Investments | C11: 0
B12: Other Assets | C12: 0
B14: Liabilities | C14: Amount
B15: Credit card debt | C15: 0
B16: Personal Loans | C16: 0
B17: Mortgage Balance | C17: 0
B18: Debt | C18: 0
B19: Any Obligations | C19: 0
B21: Net Worth | C21: =SUM(Asset_table[Amount])-SUM(Liabilities_Table[Amount]) -> 1339.425
B23: Goals
A24: FALSE | B24: {=_xlfn.UNIQUE(_xlfn._xlws.FILTER(_xlfn.VSTACK(Goal_todo[Goal], Goal_done[Goal]), _xlfn.VSTACK(Goal_todo[Goal], Goal_done[Goal])<>""))} -> Emergency Fund | C24: =VLOOKUP(B24,Goal_todo[],4,FALSE) -> 0.1339
A25: =ISNUMBER(MATCH(B25, Goal_done[Goal], 0)) -> FALSE | B25: Car Emergency Fund | C25: =VLOOKUP(B25,Goal_todo[],4,FALSE) -> 0.1674
A26: =ISNUMBER(MATCH(B26, Goal_done[Goal], 0)) -> FALSE | B26: Travel | C26: =VLOOKUP(B26,Goal_todo[],4,FALSE) -> 0.2679
A27: =ISNUMBER(MATCH(B27, Goal_done[Goal], 0)) -> FALSE | B27: House Deposit | C27: =VLOOKUP(B27,Goal_todo[],4,FALSE) -> 0.0134
A28: =ISNUMBER(MATCH(B28, Goal_done[Goal], 0)) -> FALSE | B28: Retirement | C28: =VLOOKUP(B28,Goal_todo[],4,FALSE) -> 0.0054
A29: =ISNUMBER(MATCH(B29, Goal_done[Goal], 0)) -> TRUE | B29: Mobile | C29: =IF(COUNTIF(Goal_done[Goal], B29), _xlfn.NUMBERVALUE(100%), VLOOKUP(B29, Goal_todo[], 4, FALSE)) -> 1
B31: Saving Rate | C31: =Summary!B24 -> 0.66957022

Sheet Resources
A1: Category | B1: Type | D1: Date | E1: DayNum | F1: Daily Income | G1: Daily Expense | H1: Balance | J1: forecast_date | K1: Forecast_daynum | L1: Forecast_income | M1: Forecast_Expense | N1: Forecasted_Total | Q1: Daynum | R1: Date | S1: Daily total | T1: Forecasted Total
A2: Salary | B2: Income | D2: {=_xlfn._xlws.SORT( _xlfn.UNIQUE( _xlfn._xlws.FILTER( Txn_table[Date], Txn_table[Date] <> "" ) ) )} -> 45658 | E2: {=_xlfn.SEQUENCE( ROWS(_xlfn.ANCHORARRAY(D2)), 1, 1, 1 )} -> 1 | F2: {=SUMIFS( Txn_table[Amount], Txn_table[Type (Income/Expense)], "Income", Txn_table[Date],_xlfn.ANCHORARRAY( D2) )} -> 2142.5 | G2: {=SUMIFS( Txn_table[Amount], Txn_table[Type (Income/Expense)], "Expense", Txn_table[Date],_xlfn.ANCHORARRAY(D2) )} -> 375 | H2: =F2-G2 -> 1767.5 | J2: {=_xlfn.ANCHORARRAY(D2)+6} -> 45664 | K2: {=_xlfn.ANCHORARRAY(E2)+6} -> 7 | L2: {=_xlfn.FORECAST.LINEAR(_xlfn.ANCHORARRAY( K2),_xlfn.ANCHORARRAY( F2),_xlfn.ANCHORARRAY( E2))} -> -382.58929 | M2: {=_xlfn.FORECAST.LINEAR(_xlfn.ANCHORARRAY( K2),_xlfn.ANCHORARRAY( G2),_xlfn.ANCHORARRAY( E2))} -> -10.678571 | N2: {=_xlfn.FORECAST.LINEAR(_xlfn.ANCHORARRAY( K2), H2:H8, dateIndex)} -> 1482.0357 | Q2: {=_xlfn.VSTACK(_xlfn.ANCHORARRAY(E2),_xlfn.ANCHORARRAY( K2))} -> 1 | R2: {=_xlfn.VSTACK(_xlfn.ANCHORARRAY(D2),_xlfn.ANCHORARRAY( J2))} -> 45658 | S2: {=H2:H8} -> 1767.5
A3: Bonus | B3: Income | D3: 45659 | E3: 2 | F3: 0 | G3: 45 | H3: =H2+F3-G3 -> 1722.5 | J3: 45665 | K3: 8 | L3: -612.14286 | M3: -45.714286 | N3: 1434.5 | Q3: 2 | R3: 45659 | S3: 1722.5
A4: Food | B4: Expense (Variable) | D4: 45660 | E4: 3 | F4: 0 | G4: 55 | H4: =H3+F4-G4 -> 1667.5 | J4: 45666 | K4: 9 | L4: -841.69643 | M4: -80.75 | N4: 1386.9643 | Q4: 3 | R4: 45660 | S4: 1667.5
A5: Rent | B5: Expense (Fixed) | D5: 45661 | E5: 4 | F5: 0 | G5: 43 | H5: =H4+F5-G5 -> 1624.5 | J5: 45667 | K5: 10 | L5: -1071.25 | M5: -115.78571 | N5: 1339.4286 | Q5: 4 | R5: 45661 | S5: 1624.5
A6: Travel | B6: Expense (Variable) | D6: 45662 | E6: 5 | F6: 0 | G6: 46 | H6: =H5+F6-G6 -> 1578.5 | J6: 45668 | K6: 11 | L6: -1300.8036 | M6: -150.82143 | N6: 1291.8929 | Q6: 5 | R6: 45662 | S6: 1578.5
A7: Car Petrol | B7: Expense (Variable) | D7: 45663 | E7: 6 | F7: 0 | G7: 48 | H7: =H6+F7-G7 -> 1530.5 | J7: 45669 | K7: 12 | L7: -1530.3571 | M7: -185.85714 | N7: 1244.3571 | Q7: 6 | R7: 45663 | S7: 1530.5
A8: Mobile Bills | B8: Expense (Fixed) | D8: 45664 | E8: 7 | F8: 0 | G8: 49 | H8: =H7+F8-G8 -> 1481.5 | J8: 45670 | K8: 13 | L8: -1759.9107 | M8: -220.89286 | N8: 1196.8214 | Q8: 7 | R8: 45664 | S8: 1481.5
Q9: 7 | R9: 45664 | T9: {=_xlfn.ANCHORARRAY(N2)} -> 1482.0357
Q10: 8 | R10: 45665 | T10: 1434.5
Q11: 9 | R11: 45666 | T11: 1386.9643
Q12: 10 | R12: 45667 | T12: 1339.4286
Q13: 11 | R13: 45668 | T13: 1291.8929
Q14: 12 | R14: 45669 | T14: 1244.3571
Q15: 13 | R15: 45670 | T15: 1196.8214
